Metadata-Version: 1.0
Name: cvtoolkit
Version: 0.0.0
Summary: Computer Vision Tool kit.
Home-page: UNKNOWN
Author: ZQPei
Author-email: peiziqiang@gmail.com
License: MIT
Platform: all
